Workbook
Name ClientList: 'Clients'!$A$2:$A$200
Name ServiceList: 'Services & Rates'!$A$2:$A$30

Sheet START HERE
B2: WELCOME TO YOUR CLEANING BUSINESS CLIENT CRM
B3: Made for house cleaners, maid services and cleaning companies. Everything your business needs — clients, how to get into each home, the scope of each job, your schedule and your money — in one place. No apps, no monthly software fee, nothing to install.
B5: STEP 1 — MAKE YOUR OWN COPY (do this first!)
B6: USING GOOGLE SHEETS (free): 1. Go to sheets.google.com and sign in. 2. Click the folder icon (Open file picker), choose "Upload", and drop this file in. 3. It opens right in Google Sheets — then click File > Save as Google Sheets so it lives in your Drive forever.
B7: USING EXCEL: just open the file and File > Save As with your business name. Done.
B9: STEP 2 — KNOW YOUR COLORS
B10: WHITE cells = yours. Type anything.
B11: LIGHT GRAY cells = the spreadsheet's. They calculate themselves (the rate on each clean, invoice totals, the Next Clean Due date, the whole Dashboard). Don't type in them — if you ever do by accident, just press Ctrl+Z (Cmd+Z on Mac).
B12: Cells with a little arrow = dropdowns. Click the arrow and pick — never type these by hand, so names always match everywhere.
B14: STEP 3 — SET UP IN THIS ORDER
B15: 1. SERVICES & RATES — change the service names and prices to yours (Standard Clean, Deep Clean, Move-Out, your Recurring rate, your hourly rate, and add-ons like inside fridge / oven / windows). The Schedule tab fills in the price from this list automatically.
B16: 2. CLIENTS — one row per client. Phone, email, the service address, and the part free tools never have room for: HOW YOU GET IN. Key location, lockbox code, alarm code and garage code each get their own column. Also: pets on site, who supplies the products (and any allergies / scent rules), preferred contact and an Active / Inactive / Waitlist status. Tip: type the word CAUTION anywhere in "Pets on Site" or "Notes" and the whole row turns red — a loose dog or a finicky alarm is the last thing you want to forget on the doorstep.
... B33: Questions? Message me on Etsy any time — happy to help. Enjoy!

Sheet Dashboard
B2: CLEANING BUSINESS CLIENT CRM — DASHBOARD
B3: ="Everything on this page updates itself — nothing to type here. Today: "&TEXT(TODAY(),"mmm d, yyyy")
B5: ACTIVE CLIENTS | E5: CLEANS THIS MONTH | H5: CLEANS THIS WEEK
B6: =COUNTIF('Clients'!$M:$M,"Active") | E6: =COUNTIFS('Schedule'!$E:$E,"Done",'Schedule'!$A:$A,">="&DATE(YEAR(TODAY()),MONTH(TODAY()),1),'Schedule'!$A:$A,"<"&DATE(YEAR(TODAY()),MONTH(TODAY())+1,1)) | H6: =COUNTIFS('Schedule'!$A:$A,">="&(TODAY()-WEEKDAY(TODAY(),2)+1),'Schedule'!$A:$A,"<="&(TODAY()-WEEKDAY(TODAY(),2)+1)+6,'Schedule'!$E:$E,"<>Cancelled")
B8: CLEANS TODAY | E8: REVENUE THIS MONTH | H8: UNPAID BALANCE
B9: =COUNTIFS('Schedule'!$A:$A,TODAY(),'Schedule'!$E:$E,"<>Cancelled") | E9: =SUMIFS('Schedule'!$D:$D,'Schedule'!$E:$E,"Done",'Schedule'!$A:$A,">="&DATE(YEAR(TODAY()),MONTH(TODAY()),1),'Schedule'!$A:$A,"<"&DATE(YEAR(TODAY()),MONTH(TODAY())+1,1)) | H9: =SUMIFS('Schedule'!$D:$D,'Schedule'!$E:$E,"Done",'Schedule'!$F:$F,"<>Yes")
B12: TOP CLIENTS (completed cleans, all time)
B13: Rank | C13: Client | H13: Revenue | O13: engine ↓ | P13: do not edit
B14: 1 | C14: =IFERROR(INDEX($P$14:$P$33,MATCH(LARGE($O$14:$O$33,1),$O$14:$O$33,0)),"—") | H14: =IFERROR(ROUND(LARGE($O$14:$O$33,1),2),"") | O14: =IF('Clients'!A2="","",SUMIFS('Schedule'!$D:$D,'Schedule'!$B:$B,'Clients'!A2,'Schedule'!$E:$E,"Done")+ROW()/10000000) | P14: =IF($O14="","",'Clients'!A2)
B15: 2 | C15: =IFERROR(INDEX($P$14:$P$33,MATCH(LARGE($O$14:$O$33,2),$O$14:$O$33,0)),"—") | H15: =IFERROR(ROUND(LARGE($O$14:$O$33,2),2),"") | O15: =IF('Clients'!A3="","",SUMIFS('Schedule'!$D:$D,'Schedule'!$B:$B,'Clients'!A3,'Schedule'!$E:$E,"Done")+ROW()/10000000) | P15: =IF($O15="","",'Clients'!A3)
B16: 3 | C16: =IFERROR(INDEX($P$14:$P$33,MATCH(LARGE($O$14:$O$33,3),$O$14:$O$33,0)),"—") | H16: =IFERROR(ROUND(LARGE($O$14:$O$33,3),2),"") | O16: =IF('Clients'!A4="","",SUMIFS('Schedule'!$D:$D,'Schedule'!$B:$B,'Clients'!A4,'Schedule'!$E:$E,"Done")+ROW()/10000000) | P16: =IF($O16="","",'Clients'!A4)
B17: 4 | C17: =IFERROR(INDEX($P$14:$P$33,MATCH(LARGE($O$14:$O$33,4),$O$14:$O$33,0)),"—") | H17: =IFERROR(ROUND(LARGE($O$14:$O$33,4),2),"") | O17: =IF('Clients'!A5="","",SUMIFS('Schedule'!$D:$D,'Schedule'!$B:$B,'Clients'!A5,'Schedule'!$E:$E,"Done")+ROW()/10000000) | P17: =IF($O17="","",'Clients'!A5)
B18: 5 | C18: =IFERROR(INDEX($P$14:$P$33,MATCH(LARGE($O$14:$O$33,5),$O$14:$O$33,0)),"—") | H18: =IFERROR(ROUND(LARGE($O$14:$O$33,5),2),"") | O18: =IF('Clients'!A6="","",SUMIFS('Schedule'!$D:$D,'Schedule'!$B:$B,'Clients'!A6,'Schedule'!$E:$E,"Done")+ROW()/10000000) | P18: =IF($O18="","",'Clients'!A6)
O19: =IF('Clients'!A7="","",SUMIFS('Schedule'!$D:$D,'Schedule'!$B:$B,'Clients'!A7,'Schedule'!$E:$E,"Done")+ROW()/10000000) | P19: =IF($O19="","",'Clients'!A7)
O20: =IF('Clients'!A8="","",SUMIFS('Schedule'!$D:$D,'Schedule'!$B:$B,'Clients'!A8,'Schedule'!$E:$E,"Done")+ROW()/10000000) | P20: =IF($O20="","",'Clients'!A8)
B21: Top-client list scans your first 20 client rows. Hidden columns O-P do the math — leave them alone (Format > Unhide if you're curious). | O21: =IF('Clients'!A9="","",SUMIFS('Schedule'!$D:$D,'Schedule'!$B:$B,'Clients'!A9,'Schedule'!$E:$E,"Done")+ROW()/10000000) | P21: =IF($O21="","",'Clients'!A9)
O22: =IF('Clients'!A10="","",SUMIFS('Schedule'!$D:$D,'Schedule'!$B:$B,'Clients'!A10,'Schedule'!$E:$E,"Done")+ROW()/10000000) | P22: =IF($O22="","",'Clients'!A10)
O23: =IF('Clients'!A11="","",SUMIFS('Schedule'!$D:$D,'Schedule'!$B:$B,'Clients'!A11,'Schedule'!$E:$E,"Done")+ROW()/10000000) | P23: =IF($O23="","",'Clients'!A11)
O24: =IF('Clients'!A12="","",SUMIFS('Schedule'!$D:$D,'Schedule'!$B:$B,'Clients'!A12,'Schedule'!$E:$E,"Done")+ROW()/10000000) | P24: =IF($O24="","",'Clients'!A12)
O25: =IF('Clients'!A13="","",SUMIFS('Schedule'!$D:$D,'Schedule'!$B:$B,'Clients'!A13,'Schedule'!$E:$E,"Done")+ROW()/10000000) | P25: =IF($O25="","",'Clients'!A13)
O26: =IF('Clients'!A14="","",SUMIFS('Schedule'!$D:$D,'Schedule'!$B:$B,'Clients'!A14,'Schedule'!$E:$E,"Done")+ROW()/10000000) | P26: =IF($O26="","",'Clients'!A14)
O27: =IF('Clients'!A15="","",SUMIFS('Schedule'!$D:$D,'Schedule'!$B:$B,'Clients'!A15,'Schedule'!$E:$E,"Done")+ROW()/10000000) | P27: =IF($O27="","",'Clients'!A15)
O28: =IF('Clients'!A16="","",SUMIFS('Schedule'!$D:$D,'Schedule'!$B:$B,'Clients'!A16,'Schedule'!$E:$E,"Done")+ROW()/10000000) | P28: =IF($O28="","",'Clients'!A16)
O29: =IF('Clients'!A17="","",SUMIFS('Schedule'!$D:$D,'Schedule'!$B:$B,'Clients'!A17,'Schedule'!$E:$E,"Done")+ROW()/10000000) | P29: =IF($O29="","",'Clients'!A17)
O30: =IF('Clients'!A18="","",SUMIFS('Schedule'!$D:$D,'Schedule'!$B:$B,'Clients'!A18,'Schedule'!$E:$E,"Done")+ROW()/10000000) | P30: =IF($O30="","",'Clients'!A18)
O31: =IF('Clients'!A19="","",SUMIFS('Schedule'!$D:$D,'Schedule'!$B:$B,'Clients'!A19,'Schedule'!$E:$E,"Done")+ROW()/10000000) | P31: =IF($O31="","",'Clients'!A19)
O32: =IF('Clients'!A20="","",SUMIFS('Schedule'!$D:$D,'Schedule'!$B:$B,'Clients'!A20,'Schedule'!$E:$E,"Done")+ROW()/10000000) | P32: =IF($O32="","",'Clients'!A20)
O33: =IF('Clients'!A21="","",SUMIFS('Schedule'!$D:$D,'Schedule'!$B:$B,'Clients'!A21,'Schedule'!$E:$E,"Done")+ROW()/10000000) | P33: =IF($O33="","",'Clients'!A21)

Sheet Clients
A1: Client Name | B1: Phone | C1: Email | D1: Service Address | E1: Entry / Key Location | F1: Lockbox Code | G1: Alarm Code | H1: Garage Code | I1: Pets on Site | J1: Products / Allergies | K1: Who Supplies | L1: Preferred Contact | M1: Status | N1: Notes
A2: Sofia Delgado | B2: (555) 233-9087 | C2: sofia.d@example.com | D2: 418 Maple Ct, Riverside | E2: Side gate — key under blue planter on back porch | F2: N/A | G2: 2255 # | H2: 1490 | I2: Golden retriever 'Biscuit' — friendly, keep in the yard | J2: Client supplies; fragrance-free only (asthma) | K2: Client supplies | L2: Text | M2: Active | N2: Weekly, Fri mornings — SAMPLE ROW, delete me
A3: Marcus Reilly | B3: (555) 661-2048 | C3: marcus.r@example.com | D3: 77 Birchwood Ln, Apt 3B | E3: Front desk holds a spare key — ask for unit 3B | F3: 8830 | G3: none | H3: none | I3: No pets | J3: I bring all supplies | K3: I supply | L3: Call | M3: Active | N3: Biweekly — elevator building — SAMPLE ROW, delete me
A4: Priya Nadar | B4: (555) 902-7715 | C4: priya.n@example.com | D4: 1205 Kestrel Dr | E4: Lockbox on the hose bib, back patio | F4: 5127 | G4: 4400 (code word: Willow) | H4: 2213 | I4: CAUTION: guard dog 'Rex' — owner MUST crate before each visit; do not enter the yard until confirmed | J4: Mixed — I bring supplies, client provides hardwood cleaner | K4: Mixed | L4: Email | M4: Active | N4: Monthly deep clean — SAMPLE ROW, delete me
A5: Aaron Brooks | B5: (555) 448-1190 | C5: aaron.b@example.com | D5: 9 Sutter Pl | E5: Meet on site for the first walkthrough | F5: TBD | G5: TBD | H5: TBD | I5: Dog — confirm at walkthrough | J5: TBD at walkthrough | K5: Client supplies | L5: Text | M5: Waitlist | N5: Move-out quote requested — SAMPLE ROW, delete me

Sheet Job Details
A1: Client | B1: Bedrooms | C1: Bathrooms | D1: Sq Ft | E1: Scope / Rooms Checklist | F1: Recurring Cadence | G1: Flat Rate ($) | H1: Hourly Rate ($) | I1: Est. Hours | J1: Notes
A2: Sofia Delgado | B2: 4 | C2: 3 | D2: 2400 | E2: Whole house; hardwood + tile throughout; skip the garage | F2: Weekly | G2: 140 | H2: 45 | I2: 3 | J2: Fragrance-free products only — SAMPLE ROW, delete me
A3: Marcus Reilly | B3: 2 | C3: 2 | D3: 1100 | E3: Kitchen, 2 baths, living, 2 bedrooms; fold in-unit laundry | F3: Biweekly | G3: 110 | H3: 45 | I3: 2.5 | J3: Unit 3B, elevator building — SAMPLE ROW, delete me
A4: Priya Nadar | B4: 3 | C4: 2 | D4: 1850 | E4: Deep rotation: baseboards + inside windows monthly; confirm dog is crated first | F4: Monthly | G4: 220 | H4: 50 | I4: 4 | J4: Guard dog — confirm crated on arrival — SAMPLE ROW, delete me
A5: Aaron Brooks | B5: 3 | C5: 2 | D5: 1600 | E5: Move-out: inside cabinets, oven, fridge, interior windows | F5: One-off | G5: 300 | H5: 50 | I5: 6 | J5: Quote pending walkthrough — SAMPLE ROW, delete me

Sheet Schedule
A1: Date | B1: Client | C1: Service | D1: Rate ($) | E1: Status | F1: Paid? | G1: Next Clean Due | H1: Notes
A2: =TODAY()+0 | B2: Sofia Delgado | C2: Recurring Clean | D2: =IF($C2="","",IFERROR(VLOOKUP($C2,'Services & Rates'!$A$2:$B$30,2,FALSE),"")) | E2: Booked | F2: No | G2: =IF(OR($A2="",$B2=""),"",IFERROR(IF(VLOOKUP($B2,'Job Details'!$A$2:$J$250,6,FALSE)="Weekly",$A2+7,IF(VLOOKUP($B2,'Job Details'!$A$2:$J$250,6,FALSE)="Biweekly",$A2+14,IF(VLOOKUP($B2,'Job Details'!$A$2:$J$250,6,FALSE)="Monthly",$A2+30,""))),"")) | H2: SAMPLE — today's cleans glow blue
A3: =TODAY()-3 | B3: Marcus Reilly | C3: Recurring Clean | D3: =IF($C3="","",IFERROR(VLOOKUP($C3,'Services & Rates'!$A$2:$B$30,2,FALSE),"")) | E3: Done | F3: No | G3: =IF(OR($A3="",$B3=""),"",IFERROR(IF(VLOOKUP($B3,'Job Details'!$A$2:$J$250,6,FALSE)="Weekly",$A3+7,IF(VLOOKUP($B3,'Job Details'!$A$2:$J$250,6,FALSE)="Biweekly",$A3+14,IF(VLOOKUP($B3,'Job Details'!$A$2:$J$250,6,FALSE)="Monthly",$A3+30,""))),"")) | H3: SAMPLE — done + unpaid turns red
A4: =TODAY()-10 | B4: Sofia Delgado | C4: Recurring Clean | D4: =IF($C4="","",IFERROR(VLOOKUP($C4,'Services & Rates'!$A$2:$B$30,2,FALSE),"")) | E4: Done | F4: Yes | G4: =IF(OR($A4="",$B4=""),"",IFERROR(IF(VLOOKUP($B4,'Job Details'!$A$2:$J$250,6,FALSE)="Weekly",$A4+7,IF(VLOOKUP($B4,'Job Details'!$A$2:$J$250,6,FALSE)="Biweekly",$A4+14,IF(VLOOKUP($B4,'Job Details'!$A$2:$J$250,6,FALSE)="Monthly",$A4+30,""))),"")) | H4: SAMPLE — Next Clean Due turns amber once it is due
A5: =DATE(YEAR(TODAY()),MONTH(TODAY()),1) | B5: Sofia Delgado | C5: Deep Clean | D5: =IF($C5="","",IFERROR(VLOOKUP($C5,'Services & Rates'!$A$2:$B$30,2,FALSE),"")) | E5: Done | F5: Yes | G5: =IF(OR($A5="",$B5=""),"",IFERROR(IF(VLOOKUP($B5,'Job Details'!$A$2:$J$250,6,FALSE)="Weekly",$A5+7,IF(VLOOKUP($B5,'Job Details'!$A$2:$J$250,6,FALSE)="Biweekly",$A5+14,IF(VLOOKUP($B5,'Job Details'!$A$2:$J$250,6,FALSE)="Monthly",$A5+30,""))),"")) | H5: SAMPLE ROW — delete me
A6: =TODAY()-35 | B6: Priya Nadar | C6: Deep Clean | D6: =IF($C6="","",IFERROR(VLOOKUP($C6,'Services & Rates'!$A$2:$B$30,2,FALSE),"")) | E6: Done | F6: No | G6: =IF(OR($A6="",$B6=""),"",IFERROR(IF(VLOOKUP($B6,'Job Details'!$A$2:$J$250,6,FALSE)="Weekly",$A6+7,IF(VLOOKUP($B6,'Job Details'!$A$2:$J$250,6,FALSE)="Biweekly",$A6+14,IF(VLOOKUP($B6,'Job Details'!$A$2:$J$250,6,FALSE)="Monthly",$A6+30,""))),"")) | H6: SAMPLE — older unpaid clean (see Invoices) — delete me
A7: =TODAY()+2 | B7: Marcus Reilly | C7: Standard Clean | D7: =IF($C7="","",IFERROR(VLOOKUP($C7,'Services & Rates'!$A$2:$B$30,2,FALSE),"")) | E7: Booked | F7: No | G7: =IF(OR($A7="",$B7=""),"",IFERROR(IF(VLOOKUP($B7,'Job Details'!$A$2:$J$250,6,FALSE)="Weekly",$A7+7,IF(VLOOKUP($B7,'Job Details'!$A$2:$J$250,6,FALSE)="Biweekly",$A7+14,IF(VLOOKUP($B7,'Job Details'!$A$2:$J$250,6,FALSE)="Monthly",$A7+30,""))),"")) | H7: SAMPLE ROW — delete me
D8: =IF($C8="","",IFERROR(VLOOKUP($C8,'Services & Rates'!$A$2:$B$30,2,FALSE),"")) | G8: =IF(OR($A8="",$B8=""),"",IFERROR(IF(VLOOKUP($B8,'Job Details'!$A$2:$J$250,6,FALSE)="Weekly",$A8+7,IF(VLOOKUP($B8,'Job Details'!$A$2:$J$250,6,FALSE)="Biweekly",$A8+14,IF(VLOOKUP($B8,'Job Details'!$A$2:$J$250,6,FALSE)="Monthly",$A8+30,""))),""))
D9: =IF($C9="","",IFERROR(VLOOKUP($C9,'Services & Rates'!$A$2:$B$30,2,FALSE),"")) | G9: =IF(OR($A9="",$B9=""),"",IFERROR(IF(VLOOKUP($B9,'Job Details'!$A$2:$J$250,6,FALSE)="Weekly",$A9+7,IF(VLOOKUP($B9,'Job Details'!$A$2:$J$250,6,FALSE)="Biweekly",$A9+14,IF(VLOOKUP($B9,'Job Details'!$A$2:$J$250,6,FALSE)="Monthly",$A9+30,""))),""))
D10: =IF($C10="","",IFERROR(VLOOKUP($C10,'Services & Rates'!$A$2:$B$30,2,FALSE),"")) | G10: =IF(OR($A10="",$B10=""),"",IFERROR(IF(VLOOKUP($B10,'Job Details'!$A$2:$J$250,6,FALSE)="Weekly",$A10+7,IF(VLOOKUP($B10,'Job Details'!$A$2:$J$250,6,FALSE)="Biweekly",$A10+14,IF(VLOOKUP($B10,'Job Details'!$A$2:$J$250,6,FALSE)="Monthly",$A10+30,""))),""))
D11: =IF($C11="","",IFERROR(VLOOKUP($C11,'Services & Rates'!$A$2:$B$30,2,FALSE),"")) | G11: =IF(OR($A11="",$B11=""),"",IFERROR(IF(VLOOKUP($B11,'Job Details'!$A$2:$J$250,6,FALSE)="Weekly",$A11+7,IF(VLOOKUP($B11,'Job Details'!$A$2:$J$250,6,FALSE)="Biweekly",$A11+14,IF(VLOOKUP($B11,'Job Details'!$A$2:$J$250,6,FALSE)="Monthly",$A11+30,""))),""))
D12: =IF($C12="","",IFERROR(VLOOKUP($C12,'Services & Rates'!$A$2:$B$30,2,FALSE),"")) | G12: =IF(OR($A12="",$B12=""),"",IFERROR(IF(VLOOKUP($B12,'Job Details'!$A$2:$J$250,6,FALSE)="Weekly",$A12+7,IF(VLOOKUP($B12,'Job Details'!$A$2:$J$250,6,FALSE)="Biweekly",$A12+14,IF(VLOOKUP($B12,'Job Details'!$A$2:$J$250,6,FALSE)="Monthly",$A12+30,""))),""))
D13: =IF($C13="","",IFERROR(VLOOKUP($C13,'Services & Rates'!$A$2:$B$30,2,FALSE),"")) | G13: =IF(OR($A13="",$B13=""),"",IFERROR(IF(VLOOKUP($B13,'Job Details'!$A$2:$J$250,6,FALSE)="Weekly",$A13+7,IF(VLOOKUP($B13,'Job Details'!$A$2:$J$250,6,FALSE)="Biweekly",$A13+14,IF(VLOOKUP($B13,'Job Details'!$A$2:$J$250,6,FALSE)="Monthly",$A13+30,""))),""))
D14: =IF($C14="","",IFERROR(VLOOKUP($C14,'Services & Rates'!$A$2:$B$30,2,FALSE),"")) | G14: =IF(OR($A14="",$B14=""),"",IFERROR(IF(VLOOKUP($B14,'Job Details'!$A$2:$J$250,6,FALSE)="Weekly",$A14+7,IF(VLOOKUP($B14,'Job Details'!$A$2:$J$250,6,FALSE)="Biweekly",$A14+14,IF(VLOOKUP($B14,'Job Details'!$A$2:$J$250,6,FALSE)="Monthly",$A14+30,""))),""))
D15: =IF($C15="","",IFERROR(VLOOKUP($C15,'Services & Rates'!$A$2:$B$30,2,FALSE),"")) | G15: =IF(OR($A15="",$B15=""),"",IFERROR(IF(VLOOKUP($B15,'Job Details'!$A$2:$J$250,6,FALSE)="Weekly",$A15+7,IF(VLOOKUP($B15,'Job Details'!$A$2:$J$250,6,FALSE)="Biweekly",$A15+14,IF(VLOOKUP($B15,'Job Details'!$A$2:$J$250,6,FALSE)="Monthly",$A15+30,""))),""))
D16: =IF($C16="","",IFERROR(VLOOKUP($C16,'Services & Rates'!$A$2:$B$30,2,FALSE),"")) | G16: =IF(OR($A16="",$B16=""),"",IFERROR(IF(VLOOKUP($B16,'Job Details'!$A$2:$J$250,6,FALSE)="Weekly",$A16+7,IF(VLOOKUP($B16,'Job Details'!$A$2:$J$250,6,FALSE)="Biweekly",$A16+14,IF(VLOOKUP($B16,'Job Details'!$A$2:$J$250,6,FALSE)="Monthly",$A16+30,""))),""))
D17: =IF($C17="","",IFERROR(VLOOKUP($C17,'Services & Rates'!$A$2:$B$30,2,FALSE),"")) | G17: =IF(OR($A17="",$B17=""),"",IFERROR(IF(VLOOKUP($B17,'Job Details'!$A$2:$J$250,6,FALSE)="Weekly",$A17+7,IF(VLOOKUP($B17,'Job Details'!$A$2:$J$250,6,FALSE)="Biweekly",$A17+14,IF(VLOOKUP($B17,'Job Details'!$A$2:$J$250,6,FALSE)="Monthly",$A17+30,""))),""))
D18: =IF($C18="","",IFERROR(VLOOKUP($C18,'Services & Rates'!$A$2:$B$30,2,FALSE),"")) | G18: =IF(OR($A18="",$B18=""),"",IFERROR(IF(VLOOKUP($B18,'Job Details'!$A$2:$J$250,6,FALSE)="Weekly",$A18+7,IF(VLOOKUP($B18,'Job Details'!$A$2:$J$250,6,FALSE)="Biweekly",$A18+14,IF(VLOOKUP($B18,'Job Details'!$A$2:$J$250,6,FALSE)="Monthly",$A18+30,""))),""))
D19: =IF($C19="","",IFERROR(VLOOKUP($C19,'Services & Rates'!$A$2:$B$30,2,FALSE),"")) | G19: =IF(OR($A19="",$B19=""),"",IFERROR(IF(VLOOKUP($B19,'Job Details'!$A$2:$J$250,6,FALSE)="Weekly",$A19+7,IF(VLOOKUP($B19,'Job Details'!$A$2:$J$250,6,FALSE)="Biweekly",$A19+14,IF(VLOOKUP($B19,'Job Details'!$A$2:$J$250,6,FALSE)="Monthly",$A19+30,""))),""))
... D250: =IF($C250="","",IFERROR(VLOOKUP($C250,'Services & Rates'!$A$2:$B$30,2,FALSE),"")) | G250: =IF(OR($A250="",$B250=""),"",IFERROR(IF(VLOOKUP($B250,'Job Details'!$A$2:$J$250,6,FALSE)="Weekly",$A250+7,IF(VLOOKUP($B250,'Job Details'!$A$2:$J$250,6,FALSE)="Biweekly",$A250+14,IF(VLOOKUP($B250,'Job Details'!$A$2:$J$250,6,FALSE)="Monthly",$A250+30,""))),""))

Sheet Invoices & Payments
A1: Invoice # | B1: Client | C1: Period Start | D1: Period End | E1: Invoice Total ($) | F1: Balance Due ($) | G1: Date Sent | H1: Date Paid | I1: Status | J1: Notes
A2: INV-2001 | B2: Sofia Delgado | C2: =TODAY()-40 | D2: =TODAY()+1 | E2: =IF(OR($B2="",$C2="",$D2=""),"",SUMIFS('Schedule'!$D:$D,'Schedule'!$B:$B,$B2,'Schedule'!$E:$E,"Done",'Schedule'!$A:$A,">="&$C2,'Schedule'!$A:$A,"<="&$D2)) | F2: =IF(OR($B2="",$C2="",$D2=""),"",SUMIFS('Schedule'!$D:$D,'Schedule'!$B:$B,$B2,'Schedule'!$E:$E,"Done",'Schedule'!$A:$A,">="&$C2,'Schedule'!$A:$A,"<="&$D2,'Schedule'!$F:$F,"<>Yes")) | G2: =TODAY()-30 | H2: =TODAY()-25 | I2: Paid | J2: SAMPLE ROW — delete me
A3: INV-2002 | B3: Marcus Reilly | C3: =TODAY()-8 | D3: =TODAY()+3 | E3: =IF(OR($B3="",$C3="",$D3=""),"",SUMIFS('Schedule'!$D:$D,'Schedule'!$B:$B,$B3,'Schedule'!$E:$E,"Done",'Schedule'!$A:$A,">="&$C3,'Schedule'!$A:$A,"<="&$D3)) | F3: =IF(OR($B3="",$C3="",$D3=""),"",SUMIFS('Schedule'!$D:$D,'Schedule'!$B:$B,$B3,'Schedule'!$E:$E,"Done",'Schedule'!$A:$A,">="&$C3,'Schedule'!$A:$A,"<="&$D3,'Schedule'!$F:$F,"<>Yes")) | G3: =TODAY()+0 | I3: Sent | J3: SAMPLE ROW — delete me
A4: INV-2003 | B4: Priya Nadar | C4: =TODAY()-45 | D4: =TODAY()-2 | E4: =IF(OR($B4="",$C4="",$D4=""),"",SUMIFS('Schedule'!$D:$D,'Schedule'!$B:$B,$B4,'Schedule'!$E:$E,"Done",'Schedule'!$A:$A,">="&$C4,'Schedule'!$A:$A,"<="&$D4)) | F4: =IF(OR($B4="",$C4="",$D4=""),"",SUMIFS('Schedule'!$D:$D,'Schedule'!$B:$B,$B4,'Schedule'!$E:$E,"Done",'Schedule'!$A:$A,">="&$C4,'Schedule'!$A:$A,"<="&$D4,'Schedule'!$F:$F,"<>Yes")) | G4: =TODAY()-18 | I4: Overdue | J4: SAMPLE ROW — delete me
E5: =IF(OR($B5="",$C5="",$D5=""),"",SUMIFS('Schedule'!$D:$D,'Schedule'!$B:$B,$B5,'Schedule'!$E:$E,"Done",'Schedule'!$A:$A,">="&$C5,'Schedule'!$A:$A,"<="&$D5)) | F5: =IF(OR($B5="",$C5="",$D5=""),"",SUMIFS('Schedule'!$D:$D,'Schedule'!$B:$B,$B5,'Schedule'!$E:$E,"Done",'Schedule'!$A:$A,">="&$C5,'Schedule'!$A:$A,"<="&$D5,'Schedule'!$F:$F,"<>Yes"))
E6: =IF(OR($B6="",$C6="",$D6=""),"",SUMIFS('Schedule'!$D:$D,'Schedule'!$B:$B,$B6,'Schedule'!$E:$E,"Done",'Schedule'!$A:$A,">="&$C6,'Schedule'!$A:$A,"<="&$D6)) | F6: =IF(OR($B6="",$C6="",$D6=""),"",SUMIFS('Schedule'!$D:$D,'Schedule'!$B:$B,$B6,'Schedule'!$E:$E,"Done",'Schedule'!$A:$A,">="&$C6,'Schedule'!$A:$A,"<="&$D6,'Schedule'!$F:$F,"<>Yes"))
E7: =IF(OR($B7="",$C7="",$D7=""),"",SUMIFS('Schedule'!$D:$D,'Schedule'!$B:$B,$B7,'Schedule'!$E:$E,"Done",'Schedule'!$A:$A,">="&$C7,'Schedule'!$A:$A,"<="&$D7)) | F7: =IF(OR($B7="",$C7="",$D7=""),"",SUMIFS('Schedule'!$D:$D,'Schedule'!$B:$B,$B7,'Schedule'!$E:$E,"Done",'Schedule'!$A:$A,">="&$C7,'Schedule'!$A:$A,"<="&$D7,'Schedule'!$F:$F,"<>Yes"))
E8: =IF(OR($B8="",$C8="",$D8=""),"",SUMIFS('Schedule'!$D:$D,'Schedule'!$B:$B,$B8,'Schedule'!$E:$E,"Done",'Schedule'!$A:$A,">="&$C8,'Schedule'!$A:$A,"<="&$D8)) | F8: =IF(OR($B8="",$C8="",$D8=""),"",SUMIFS('Schedule'!$D:$D,'Schedule'!$B:$B,$B8,'Schedule'!$E:$E,"Done",'Schedule'!$A:$A,">="&$C8,'Schedule'!$A:$A,"<="&$D8,'Schedule'!$F:$F,"<>Yes"))
E9: =IF(OR($B9="",$C9="",$D9=""),"",SUMIFS('Schedule'!$D:$D,'Schedule'!$B:$B,$B9,'Schedule'!$E:$E,"Done",'Schedule'!$A:$A,">="&$C9,'Schedule'!$A:$A,"<="&$D9)) | F9: =IF(OR($B9="",$C9="",$D9=""),"",SUMIFS('Schedule'!$D:$D,'Schedule'!$B:$B,$B9,'Schedule'!$E:$E,"Done",'Schedule'!$A:$A,">="&$C9,'Schedule'!$A:$A,"<="&$D9,'Schedule'!$F:$F,"<>Yes"))
E10: =IF(OR($B10="",$C10="",$D10=""),"",SUMIFS('Schedule'!$D:$D,'Schedule'!$B:$B,$B10,'Schedule'!$E:$E,"Done",'Schedule'!$A:$A,">="&$C10,'Schedule'!$A:$A,"<="&$D10)) | F10: =IF(OR($B10="",$C10="",$D10=""),"",SUMIFS('Schedule'!$D:$D,'Schedule'!$B:$B,$B10,'Schedule'!$E:$E,"Done",'Schedule'!$A:$A,">="&$C10,'Schedule'!$A:$A,"<="&$D10,'Schedule'!$F:$F,"<>Yes"))
E11: =IF(OR($B11="",$C11="",$D11=""),"",SUMIFS('Schedule'!$D:$D,'Schedule'!$B:$B,$B11,'Schedule'!$E:$E,"Done",'Schedule'!$A:$A,">="&$C11,'Schedule'!$A:$A,"<="&$D11)) | F11: =IF(OR($B11="",$C11="",$D11=""),"",SUMIFS('Schedule'!$D:$D,'Schedule'!$B:$B,$B11,'Schedule'!$E:$E,"Done",'Schedule'!$A:$A,">="&$C11,'Schedule'!$A:$A,"<="&$D11,'Schedule'!$F:$F,"<>Yes"))
E12: =IF(OR($B12="",$C12="",$D12=""),"",SUMIFS('Schedule'!$D:$D,'Schedule'!$B:$B,$B12,'Schedule'!$E:$E,"Done",'Schedule'!$A:$A,">="&$C12,'Schedule'!$A:$A,"<="&$D12)) | F12: =IF(OR($B12="",$C12="",$D12=""),"",SUMIFS('Schedule'!$D:$D,'Schedule'!$B:$B,$B12,'Schedule'!$E:$E,"Done",'Schedule'!$A:$A,">="&$C12,'Schedule'!$A:$A,"<="&$D12,'Schedule'!$F:$F,"<>Yes"))
E13: =IF(OR($B13="",$C13="",$D13=""),"",SUMIFS('Schedule'!$D:$D,'Schedule'!$B:$B,$B13,'Schedule'!$E:$E,"Done",'Schedule'!$A:$A,">="&$C13,'Schedule'!$A:$A,"<="&$D13)) | F13: =IF(OR($B13="",$C13="",$D13=""),"",SUMIFS('Schedule'!$D:$D,'Schedule'!$B:$B,$B13,'Schedule'!$E:$E,"Done",'Schedule'!$A:$A,">="&$C13,'Schedule'!$A:$A,"<="&$D13,'Schedule'!$F:$F,"<>Yes"))
E14: =IF(OR($B14="",$C14="",$D14=""),"",SUMIFS('Schedule'!$D:$D,'Schedule'!$B:$B,$B14,'Schedule'!$E:$E,"Done",'Schedule'!$A:$A,">="&$C14,'Schedule'!$A:$A,"<="&$D14)) | F14: =IF(OR($B14="",$C14="",$D14=""),"",SUMIFS('Schedule'!$D:$D,'Schedule'!$B:$B,$B14,'Schedule'!$E:$E,"Done",'Schedule'!$A:$A,">="&$C14,'Schedule'!$A:$A,"<="&$D14,'Schedule'!$F:$F,"<>Yes"))
E15: =IF(OR($B15="",$C15="",$D15=""),"",SUMIFS('Schedule'!$D:$D,'Schedule'!$B:$B,$B15,'Schedule'!$E:$E,"Done",'Schedule'!$A:$A,">="&$C15,'Schedule'!$A:$A,"<="&$D15)) | F15: =IF(OR($B15="",$C15="",$D15=""),"",SUMIFS('Schedule'!$D:$D,'Schedule'!$B:$B,$B15,'Schedule'!$E:$E,"Done",'Schedule'!$A:$A,">="&$C15,'Schedule'!$A:$A,"<="&$D15,'Schedule'!$F:$F,"<>Yes"))
E16: =IF(OR($B16="",$C16="",$D16=""),"",SUMIFS('Schedule'!$D:$D,'Schedule'!$B:$B,$B16,'Schedule'!$E:$E,"Done",'Schedule'!$A:$A,">="&$C16,'Schedule'!$A:$A,"<="&$D16)) | F16: =IF(OR($B16="",$C16="",$D16=""),"",SUMIFS('Schedule'!$D:$D,'Schedule'!$B:$B,$B16,'Schedule'!$E:$E,"Done",'Schedule'!$A:$A,">="&$C16,'Schedule'!$A:$A,"<="&$D16,'Schedule'!$F:$F,"<>Yes"))
... E100: =IF(OR($B100="",$C100="",$D100=""),"",SUMIFS('Schedule'!$D:$D,'Schedule'!$B:$B,$B100,'Schedule'!$E:$E,"Done",'Schedule'!$A:$A,">="&$C100,'Schedule'!$A:$A,"<="&$D100)) | F100: =IF(OR($B100="",$C100="",$D100=""),"",SUMIFS('Schedule'!$D:$D,'Schedule'!$B:$B,$B100,'Schedule'!$E:$E,"Done",'Schedule'!$A:$A,">="&$C100,'Schedule'!$A:$A,"<="&$D100,'Schedule'!$F:$F,"<>Yes"))

Sheet Services & Rates
A1: Service | B1: Rate ($) | C1: Unit / Time | D1: Notes
A2: Standard Clean | B2: 120 | C2: Flat / ~3 hrs | D2: Kitchen, baths, floors, dusting, trash — a maintained home
A3: Deep Clean | B3: 250 | C3: Flat / 5-6 hrs | D3: Baseboards, inside windows, cabinet fronts, scrub build-up
A4: Move-Out / Move-In | B4: 320 | C4: Flat / 6-8 hrs | D4: Empty home: inside cabinets, oven, fridge, closets, windows
A5: Recurring Clean | B5: 100 | C5: Per visit | D5: Standard clean for weekly / biweekly / monthly regulars
A6: Hourly | B6: 45 | C6: Per hour | D6: Odd jobs or unknown scope — bill the actual time worked
A7: Add-on: Inside Fridge | B7: 35 | C7: Per item | D7: Empty, wipe and sanitize the interior
A8: Add-on: Inside Oven | B8: 35 | C8: Per item | D8: Degrease racks and interior
A9: Add-on: Interior Windows | B9: 45 | C9: Per item | D9: Interior glass + sills, standard home
A10: Add-on: Inside Cabinets | B10: 40 | C10: Per item | D10: Empty kitchen cabinets wiped inside
A11: Add-on: Laundry / Linens | B11: 25 | C11: Per load | D11: Wash, dry and fold, or strip & remake beds
A32: Edit names and rates freely — the Schedule tab looks prices up from this list automatically. Service names here must match the dropdown picks exactly (they will, if you always pick from the dropdown).
