Workbook
Name ClientList: 'Clients'!$A$2:$A$200
Name ServiceList: 'Services & Rates'!$A$2:$A$30

Sheet START HERE
B2: WELCOME TO YOUR DOG GROOMER CLIENT CRM
B3: Made for dog groomers and grooming salons. Everything your business needs — clients, dogs, cut & style history, coat details, behavior warnings, appointments and money — in one place. No apps, no monthly software fee, nothing to install.
B5: STEP 1 — MAKE YOUR OWN COPY (do this first!)
B6: USING GOOGLE SHEETS (free): 1. Go to sheets.google.com and sign in. 2. Click the folder icon (Open file picker), choose "Upload", and drop this file in. 3. It opens right in Google Sheets — then click File > Save as Google Sheets so it lives in your Drive forever.
B7: USING EXCEL: just open the file and File > Save As with your business name. Done.
B9: STEP 2 — KNOW YOUR COLORS
B10: WHITE cells = yours. Type anything.
B11: LIGHT GRAY cells = the spreadsheet's. They calculate themselves (rates, invoice totals, rebook due dates, the whole Dashboard). Don't type in them — if you ever do by accident, just press Ctrl+Z (Cmd+Z on Mac).
B12: Cells with a little arrow = dropdowns. Click the arrow and pick — never type these by hand, so names always match everywhere.
B14: STEP 3 — SET UP IN THIS ORDER
B15: 1. SERVICES & RATES — change the service names and prices to yours (full grooms by size, bath & brush, de-shed, nail trims). The Appointments tab fills in prices from this list automatically.
B16: 2. CLIENTS — one row per owner. Phone, email, preferred contact, emergency contact, vet clinic and status all live here.
... B30: Questions? Message me on Etsy any time — happy to help. Enjoy!

Sheet Dashboard
B2: DOG GROOMER CLIENT CRM — DASHBOARD
B3: ="Everything on this page updates itself — nothing to type here. Today: "&TEXT(TODAY(),"mmm d, yyyy")
B5: ACTIVE CLIENTS | E5: DOGS GROOMED THIS MONTH | H5: APPOINTMENTS THIS WEEK
B6: =COUNTIF('Clients'!$H:$H,"Active") | E6: =COUNTIFS('Appointments'!$F:$F,"Done",'Appointments'!$A:$A,">="&DATE(YEAR(TODAY()),MONTH(TODAY()),1),'Appointments'!$A:$A,"<"&DATE(YEAR(TODAY()),MONTH(TODAY())+1,1)) | H6: =COUNTIFS('Appointments'!$A:$A,">="&(TODAY()-WEEKDAY(TODAY(),2)+1),'Appointments'!$A:$A,"<="&(TODAY()-WEEKDAY(TODAY(),2)+1)+6,'Appointments'!$F:$F,"<>Cancelled")
B8: APPOINTMENTS TODAY | E8: REVENUE THIS MONTH | H8: UNPAID BALANCE
B9: =COUNTIFS('Appointments'!$A:$A,TODAY(),'Appointments'!$F:$F,"<>Cancelled") | E9: =SUMIFS('Appointments'!$E:$E,'Appointments'!$F:$F,"Done",'Appointments'!$A:$A,">="&DATE(YEAR(TODAY()),MONTH(TODAY()),1),'Appointments'!$A:$A,"<"&DATE(YEAR(TODAY()),MONTH(TODAY())+1,1)) | H9: =SUMIFS('Appointments'!$E:$E,'Appointments'!$F:$F,"Done",'Appointments'!$G:$G,"<>Yes")
B12: TOP CLIENTS (completed appointments, all time)
B13: Rank | C13: Client | H13: Revenue | O13: engine ↓ | P13: do not edit
B14: 1 | C14: =IFERROR(INDEX($P$14:$P$33,MATCH(LARGE($O$14:$O$33,1),$O$14:$O$33,0)),"—") | H14: =IFERROR(ROUND(LARGE($O$14:$O$33,1),2),"") | O14: =IF('Clients'!A2="","",SUMIFS('Appointments'!$E:$E,'Appointments'!$B:$B,'Clients'!A2,'Appointments'!$F:$F,"Done")+ROW()/10000000) | P14: =IF($O14="","",'Clients'!A2)
B15: 2 | C15: =IFERROR(INDEX($P$14:$P$33,MATCH(LARGE($O$14:$O$33,2),$O$14:$O$33,0)),"—") | H15: =IFERROR(ROUND(LARGE($O$14:$O$33,2),2),"") | O15: =IF('Clients'!A3="","",SUMIFS('Appointments'!$E:$E,'Appointments'!$B:$B,'Clients'!A3,'Appointments'!$F:$F,"Done")+ROW()/10000000) | P15: =IF($O15="","",'Clients'!A3)
B16: 3 | C16: =IFERROR(INDEX($P$14:$P$33,MATCH(LARGE($O$14:$O$33,3),$O$14:$O$33,0)),"—") | H16: =IFERROR(ROUND(LARGE($O$14:$O$33,3),2),"") | O16: =IF('Clients'!A4="","",SUMIFS('Appointments'!$E:$E,'Appointments'!$B:$B,'Clients'!A4,'Appointments'!$F:$F,"Done")+ROW()/10000000) | P16: =IF($O16="","",'Clients'!A4)
B17: 4 | C17: =IFERROR(INDEX($P$14:$P$33,MATCH(LARGE($O$14:$O$33,4),$O$14:$O$33,0)),"—") | H17: =IFERROR(ROUND(LARGE($O$14:$O$33,4),2),"") | O17: =IF('Clients'!A5="","",SUMIFS('Appointments'!$E:$E,'Appointments'!$B:$B,'Clients'!A5,'Appointments'!$F:$F,"Done")+ROW()/10000000) | P17: =IF($O17="","",'Clients'!A5)
B18: 5 | C18: =IFERROR(INDEX($P$14:$P$33,MATCH(LARGE($O$14:$O$33,5),$O$14:$O$33,0)),"—") | H18: =IFERROR(ROUND(LARGE($O$14:$O$33,5),2),"") | O18: =IF('Clients'!A6="","",SUMIFS('Appointments'!$E:$E,'Appointments'!$B:$B,'Clients'!A6,'Appointments'!$F:$F,"Done")+ROW()/10000000) | P18: =IF($O18="","",'Clients'!A6)
O19: =IF('Clients'!A7="","",SUMIFS('Appointments'!$E:$E,'Appointments'!$B:$B,'Clients'!A7,'Appointments'!$F:$F,"Done")+ROW()/10000000) | P19: =IF($O19="","",'Clients'!A7)
O20: =IF('Clients'!A8="","",SUMIFS('Appointments'!$E:$E,'Appointments'!$B:$B,'Clients'!A8,'Appointments'!$F:$F,"Done")+ROW()/10000000) | P20: =IF($O20="","",'Clients'!A8)
B21: Top-client list scans your first 20 client rows. Hidden columns O-P do the math — leave them alone (Format > Unhide if you're curious). | O21: =IF('Clients'!A9="","",SUMIFS('Appointments'!$E:$E,'Appointments'!$B:$B,'Clients'!A9,'Appointments'!$F:$F,"Done")+ROW()/10000000) | P21: =IF($O21="","",'Clients'!A9)
O22: =IF('Clients'!A10="","",SUMIFS('Appointments'!$E:$E,'Appointments'!$B:$B,'Clients'!A10,'Appointments'!$F:$F,"Done")+ROW()/10000000) | P22: =IF($O22="","",'Clients'!A10)
O23: =IF('Clients'!A11="","",SUMIFS('Appointments'!$E:$E,'Appointments'!$B:$B,'Clients'!A11,'Appointments'!$F:$F,"Done")+ROW()/10000000) | P23: =IF($O23="","",'Clients'!A11)
O24: =IF('Clients'!A12="","",SUMIFS('Appointments'!$E:$E,'Appointments'!$B:$B,'Clients'!A12,'Appointments'!$F:$F,"Done")+ROW()/10000000) | P24: =IF($O24="","",'Clients'!A12)
O25: =IF('Clients'!A13="","",SUMIFS('Appointments'!$E:$E,'Appointments'!$B:$B,'Clients'!A13,'Appointments'!$F:$F,"Done")+ROW()/10000000) | P25: =IF($O25="","",'Clients'!A13)
O26: =IF('Clients'!A14="","",SUMIFS('Appointments'!$E:$E,'Appointments'!$B:$B,'Clients'!A14,'Appointments'!$F:$F,"Done")+ROW()/10000000) | P26: =IF($O26="","",'Clients'!A14)
O27: =IF('Clients'!A15="","",SUMIFS('Appointments'!$E:$E,'Appointments'!$B:$B,'Clients'!A15,'Appointments'!$F:$F,"Done")+ROW()/10000000) | P27: =IF($O27="","",'Clients'!A15)
O28: =IF('Clients'!A16="","",SUMIFS('Appointments'!$E:$E,'Appointments'!$B:$B,'Clients'!A16,'Appointments'!$F:$F,"Done")+ROW()/10000000) | P28: =IF($O28="","",'Clients'!A16)
O29: =IF('Clients'!A17="","",SUMIFS('Appointments'!$E:$E,'Appointments'!$B:$B,'Clients'!A17,'Appointments'!$F:$F,"Done")+ROW()/10000000) | P29: =IF($O29="","",'Clients'!A17)
O30: =IF('Clients'!A18="","",SUMIFS('Appointments'!$E:$E,'Appointments'!$B:$B,'Clients'!A18,'Appointments'!$F:$F,"Done")+ROW()/10000000) | P30: =IF($O30="","",'Clients'!A18)
O31: =IF('Clients'!A19="","",SUMIFS('Appointments'!$E:$E,'Appointments'!$B:$B,'Clients'!A19,'Appointments'!$F:$F,"Done")+ROW()/10000000) | P31: =IF($O31="","",'Clients'!A19)
O32: =IF('Clients'!A20="","",SUMIFS('Appointments'!$E:$E,'Appointments'!$B:$B,'Clients'!A20,'Appointments'!$F:$F,"Done")+ROW()/10000000) | P32: =IF($O32="","",'Clients'!A20)
O33: =IF('Clients'!A21="","",SUMIFS('Appointments'!$E:$E,'Appointments'!$B:$B,'Clients'!A21,'Appointments'!$F:$F,"Done")+ROW()/10000000) | P33: =IF($O33="","",'Clients'!A21)

Sheet Clients
A1: Client Name | B1: Phone | C1: Email | D1: Preferred Contact | E1: Emergency Contact (name & phone) | F1: Vet Clinic | G1: Vet Phone | H1: Status | I1: Notes
A2: Amanda Foster | B2: (555) 214-7788 | C2: amanda.f@example.com | D2: Text | E2: Mike Foster (555) 214-7790 | F2: Lakeview Animal Hospital | G2: (555) 640-2210 | H2: Active | I2: SAMPLE ROW — delete me
A3: Derek Okafor | B3: (555) 318-2276 | C3: derek.o@example.com | D3: Call | E3: Nia Okafor (555) 318-9901 | F3: Eastside Vet Clinic | G3: (555) 772-0184 | H3: Active | I3: Prefers early morning slots — SAMPLE ROW, delete me
A4: Priya Raman | B4: (555) 467-9032 | C4: priya.r@example.com | D4: Email | E4: Dev Raman (555) 467-9033 | F4: Harbor Animal Hospital | G4: (555) 903-3341 | H4: Waitlist | I4: SAMPLE ROW — delete me

Sheet Pets
A1: Owner | B1: Dog Name | C1: Breed | D1: Age | E1: Coat Type | F1: Last Cut / Style Notes (what the owner asked for) | G1: Blade / Comb Lengths | H1: Shampoo & Products Used | I1: Skin Conditions / Allergies | J1: Behavior Notes / Warnings | K1: Matting Notes | L1: Ear / Nail / Gland Prefs
A2: Amanda Foster | B2: Murphy | C2: Goldendoodle | D2: 3 | E2: Curly | F2: Teddy-bear head, 1/2" body all over — owner wants the ears left long this time | G2: #4F body, #10 sanitary, 1/2" comb legs | H2: Oatmeal shampoo + light conditioner | I2: Sensitive skin — no perfumed finishing sprays | J2: Sweet but wiggly on the table — go slow on feet | K2: Mats behind ears & armpits when owner skips brushing — check every visit; charge de-mat fee over 15 min | L2: Grind nails (hates clippers); pluck ears; no glands (vet does) — SAMPLE ROW, delete me
A3: Derek Okafor | B3: Luna | C3: Siberian Husky | D3: 5 | E3: Double Coat | F3: De-shed only — NEVER shave (owner confirmed twice) | G3: No blades — undercoat rake + high-velocity dry | H3: De-shedding shampoo + conditioner | I3: None | J3: Vocal but friendly — sings through the whole dry | K3: None — coat well maintained between visits | L3: Nails clipped OK; ears wipe only — SAMPLE ROW, delete me
A4: Priya Raman | B4: Taco | C4: Chihuahua | D4: 8 | E4: Smooth | F4: Bath & brush; tidy face only, no body clipping | G4: #10 on face if needed | H4: Hypoallergenic shampoo | I4: Allergic to chicken-based treats | J4: CAUTION: nippy when paws are handled — muzzle for nails, treats after, keep sessions short | K4: None | L4: Nail trim every visit; glands yes — SAMPLE ROW, delete me
A5: Amanda Foster | B5: Bella | C5: Shih Tzu | D5: 6 | E5: Silky | F5: Short puppy cut, rounded face, bow on collar to finish | G5: #7F body, 3/8" comb legs | H5: Whitening shampoo (white coat), tearless face wash | I5: Tear staining — clean around eyes gently | J5: Calm, easy on the table | K5: Fine mats in leg feathering if she goes past 6 weeks | L5: Nails clipped; ears plucked; glands yes — SAMPLE ROW, delete me

Sheet Appointments
A1: Date | B1: Client | C1: Dog | D1: Service | E1: Rate ($) | F1: Status | G1: Paid? | H1: Rebook (weeks) | I1: Next Groom Due | J1: Notes
A2: =TODAY()+0 | B2: Amanda Foster | C2: Murphy | D2: Full Groom — Medium | E2: =IF($D2="","",IFERROR(VLOOKUP($D2,'Services & Rates'!$A$2:$B$30,2,FALSE),"")) | F2: Booked | G2: No | H2: 6 | I2: =IF(OR($A2="",$H2=""),"",$A2+$H2*7) | J2: SAMPLE — today's appointments glow
A3: =TODAY()-3 | B3: Priya Raman | C3: Taco | D3: Nail Trim | E3: =IF($D3="","",IFERROR(VLOOKUP($D3,'Services & Rates'!$A$2:$B$30,2,FALSE),"")) | F3: Done | G3: No | H3: 4 | I3: =IF(OR($A3="",$H3=""),"",$A3+$H3*7) | J3: SAMPLE — done + unpaid turns red
A4: =TODAY()-7 | B4: Derek Okafor | C4: Luna | D4: De-shed Treatment | E4: =IF($D4="","",IFERROR(VLOOKUP($D4,'Services & Rates'!$A$2:$B$30,2,FALSE),"")) | F4: Done | G4: No | H4: 8 | I4: =IF(OR($A4="",$H4=""),"",$A4+$H4*7) | J4: SAMPLE ROW — delete me
A5: =DATE(YEAR(TODAY()),MONTH(TODAY()),1) | B5: Amanda Foster | C5: Bella | D5: Full Groom — Small | E5: =IF($D5="","",IFERROR(VLOOKUP($D5,'Services & Rates'!$A$2:$B$30,2,FALSE),"")) | F5: Done | G5: Yes | H5: 6 | I5: =IF(OR($A5="",$H5=""),"",$A5+$H5*7) | J5: SAMPLE ROW — delete me
A6: =TODAY()-35 | B6: Amanda Foster | C6: Bella | D6: Full Groom — Small | E6: =IF($D6="","",IFERROR(VLOOKUP($D6,'Services & Rates'!$A$2:$B$30,2,FALSE),"")) | F6: Done | G6: Yes | H6: 4 | I6: =IF(OR($A6="",$H6=""),"",$A6+$H6*7) | J6: SAMPLE — overdue rebook turns amber
A7: =TODAY()+2 | B7: Derek Okafor | C7: Luna | D7: Bath & Brush | E7: =IF($D7="","",IFERROR(VLOOKUP($D7,'Services & Rates'!$A$2:$B$30,2,FALSE),"")) | F7: Booked | G7: No | I7: =IF(OR($A7="",$H7=""),"",$A7+$H7*7) | J7: SAMPLE ROW — delete me
E8: =IF($D8="","",IFERROR(VLOOKUP($D8,'Services & Rates'!$A$2:$B$30,2,FALSE),"")) | I8: =IF(OR($A8="",$H8=""),"",$A8+$H8*7)
E9: =IF($D9="","",IFERROR(VLOOKUP($D9,'Services & Rates'!$A$2:$B$30,2,FALSE),"")) | I9: =IF(OR($A9="",$H9=""),"",$A9+$H9*7)
E10: =IF($D10="","",IFERROR(VLOOKUP($D10,'Services & Rates'!$A$2:$B$30,2,FALSE),"")) | I10: =IF(OR($A10="",$H10=""),"",$A10+$H10*7)
E11: =IF($D11="","",IFERROR(VLOOKUP($D11,'Services & Rates'!$A$2:$B$30,2,FALSE),"")) | I11: =IF(OR($A11="",$H11=""),"",$A11+$H11*7)
E12: =IF($D12="","",IFERROR(VLOOKUP($D12,'Services & Rates'!$A$2:$B$30,2,FALSE),"")) | I12: =IF(OR($A12="",$H12=""),"",$A12+$H12*7)
E13: =IF($D13="","",IFERROR(VLOOKUP($D13,'Services & Rates'!$A$2:$B$30,2,FALSE),"")) | I13: =IF(OR($A13="",$H13=""),"",$A13+$H13*7)
E14: =IF($D14="","",IFERROR(VLOOKUP($D14,'Services & Rates'!$A$2:$B$30,2,FALSE),"")) | I14: =IF(OR($A14="",$H14=""),"",$A14+$H14*7)
E15: =IF($D15="","",IFERROR(VLOOKUP($D15,'Services & Rates'!$A$2:$B$30,2,FALSE),"")) | I15: =IF(OR($A15="",$H15=""),"",$A15+$H15*7)
E16: =IF($D16="","",IFERROR(VLOOKUP($D16,'Services & Rates'!$A$2:$B$30,2,FALSE),"")) | I16: =IF(OR($A16="",$H16=""),"",$A16+$H16*7)
E17: =IF($D17="","",IFERROR(VLOOKUP($D17,'Services & Rates'!$A$2:$B$30,2,FALSE),"")) | I17: =IF(OR($A17="",$H17=""),"",$A17+$H17*7)
E18: =IF($D18="","",IFERROR(VLOOKUP($D18,'Services & Rates'!$A$2:$B$30,2,FALSE),"")) | I18: =IF(OR($A18="",$H18=""),"",$A18+$H18*7)
E19: =IF($D19="","",IFERROR(VLOOKUP($D19,'Services & Rates'!$A$2:$B$30,2,FALSE),"")) | I19: =IF(OR($A19="",$H19=""),"",$A19+$H19*7)
... E250: =IF($D250="","",IFERROR(VLOOKUP($D250,'Services & Rates'!$A$2:$B$30,2,FALSE),"")) | I250: =IF(OR($A250="",$H250=""),"",$A250+$H250*7)

Sheet Invoices & Payments
A1: Invoice # | B1: Client | C1: Period Start | D1: Period End | E1: Invoice Total ($) | F1: Balance Due ($) | G1: Date Sent | H1: Date Paid | I1: Status | J1: Notes
A2: INV-1001 | B2: Amanda Foster | C2: =TODAY()-40 | D2: =TODAY()-30 | E2: =IF(OR($B2="",$C2="",$D2=""),"",SUMIFS('Appointments'!$E:$E,'Appointments'!$B:$B,$B2,'Appointments'!$F:$F,"Done",'Appointments'!$A:$A,">="&$C2,'Appointments'!$A:$A,"<="&$D2)) | F2: =IF(OR($B2="",$C2="",$D2=""),"",SUMIFS('Appointments'!$E:$E,'Appointments'!$B:$B,$B2,'Appointments'!$F:$F,"Done",'Appointments'!$A:$A,">="&$C2,'Appointments'!$A:$A,"<="&$D2,'Appointments'!$G:$G,"<>Yes")) | G2: =TODAY()-28 | H2: =TODAY()-25 | I2: Paid | J2: SAMPLE ROW — delete me
A3: INV-1002 | B3: Derek Okafor | C3: =TODAY()-8 | D3: =TODAY()+0 | E3: =IF(OR($B3="",$C3="",$D3=""),"",SUMIFS('Appointments'!$E:$E,'Appointments'!$B:$B,$B3,'Appointments'!$F:$F,"Done",'Appointments'!$A:$A,">="&$C3,'Appointments'!$A:$A,"<="&$D3)) | F3: =IF(OR($B3="",$C3="",$D3=""),"",SUMIFS('Appointments'!$E:$E,'Appointments'!$B:$B,$B3,'Appointments'!$F:$F,"Done",'Appointments'!$A:$A,">="&$C3,'Appointments'!$A:$A,"<="&$D3,'Appointments'!$G:$G,"<>Yes")) | G3: =TODAY()+0 | I3: Sent | J3: SAMPLE ROW — delete me
A4: INV-1003 | B4: Priya Raman | C4: =TODAY()-20 | D4: =TODAY()-2 | E4: =IF(OR($B4="",$C4="",$D4=""),"",SUMIFS('Appointments'!$E:$E,'Appointments'!$B:$B,$B4,'Appointments'!$F:$F,"Done",'Appointments'!$A:$A,">="&$C4,'Appointments'!$A:$A,"<="&$D4)) | F4: =IF(OR($B4="",$C4="",$D4=""),"",SUMIFS('Appointments'!$E:$E,'Appointments'!$B:$B,$B4,'Appointments'!$F:$F,"Done",'Appointments'!$A:$A,">="&$C4,'Appointments'!$A:$A,"<="&$D4,'Appointments'!$G:$G,"<>Yes")) | G4: =TODAY()-18 | I4: Overdue | J4: SAMPLE ROW — delete me
E5: =IF(OR($B5="",$C5="",$D5=""),"",SUMIFS('Appointments'!$E:$E,'Appointments'!$B:$B,$B5,'Appointments'!$F:$F,"Done",'Appointments'!$A:$A,">="&$C5,'Appointments'!$A:$A,"<="&$D5)) | F5: =IF(OR($B5="",$C5="",$D5=""),"",SUMIFS('Appointments'!$E:$E,'Appointments'!$B:$B,$B5,'Appointments'!$F:$F,"Done",'Appointments'!$A:$A,">="&$C5,'Appointments'!$A:$A,"<="&$D5,'Appointments'!$G:$G,"<>Yes"))
E6: =IF(OR($B6="",$C6="",$D6=""),"",SUMIFS('Appointments'!$E:$E,'Appointments'!$B:$B,$B6,'Appointments'!$F:$F,"Done",'Appointments'!$A:$A,">="&$C6,'Appointments'!$A:$A,"<="&$D6)) | F6: =IF(OR($B6="",$C6="",$D6=""),"",SUMIFS('Appointments'!$E:$E,'Appointments'!$B:$B,$B6,'Appointments'!$F:$F,"Done",'Appointments'!$A:$A,">="&$C6,'Appointments'!$A:$A,"<="&$D6,'Appointments'!$G:$G,"<>Yes"))
E7: =IF(OR($B7="",$C7="",$D7=""),"",SUMIFS('Appointments'!$E:$E,'Appointments'!$B:$B,$B7,'Appointments'!$F:$F,"Done",'Appointments'!$A:$A,">="&$C7,'Appointments'!$A:$A,"<="&$D7)) | F7: =IF(OR($B7="",$C7="",$D7=""),"",SUMIFS('Appointments'!$E:$E,'Appointments'!$B:$B,$B7,'Appointments'!$F:$F,"Done",'Appointments'!$A:$A,">="&$C7,'Appointments'!$A:$A,"<="&$D7,'Appointments'!$G:$G,"<>Yes"))
E8: =IF(OR($B8="",$C8="",$D8=""),"",SUMIFS('Appointments'!$E:$E,'Appointments'!$B:$B,$B8,'Appointments'!$F:$F,"Done",'Appointments'!$A:$A,">="&$C8,'Appointments'!$A:$A,"<="&$D8)) | F8: =IF(OR($B8="",$C8="",$D8=""),"",SUMIFS('Appointments'!$E:$E,'Appointments'!$B:$B,$B8,'Appointments'!$F:$F,"Done",'Appointments'!$A:$A,">="&$C8,'Appointments'!$A:$A,"<="&$D8,'Appointments'!$G:$G,"<>Yes"))
E9: =IF(OR($B9="",$C9="",$D9=""),"",SUMIFS('Appointments'!$E:$E,'Appointments'!$B:$B,$B9,'Appointments'!$F:$F,"Done",'Appointments'!$A:$A,">="&$C9,'Appointments'!$A:$A,"<="&$D9)) | F9: =IF(OR($B9="",$C9="",$D9=""),"",SUMIFS('Appointments'!$E:$E,'Appointments'!$B:$B,$B9,'Appointments'!$F:$F,"Done",'Appointments'!$A:$A,">="&$C9,'Appointments'!$A:$A,"<="&$D9,'Appointments'!$G:$G,"<>Yes"))
E10: =IF(OR($B10="",$C10="",$D10=""),"",SUMIFS('Appointments'!$E:$E,'Appointments'!$B:$B,$B10,'Appointments'!$F:$F,"Done",'Appointments'!$A:$A,">="&$C10,'Appointments'!$A:$A,"<="&$D10)) | F10: =IF(OR($B10="",$C10="",$D10=""),"",SUMIFS('Appointments'!$E:$E,'Appointments'!$B:$B,$B10,'Appointments'!$F:$F,"Done",'Appointments'!$A:$A,">="&$C10,'Appointments'!$A:$A,"<="&$D10,'Appointments'!$G:$G,"<>Yes"))
E11: =IF(OR($B11="",$C11="",$D11=""),"",SUMIFS('Appointments'!$E:$E,'Appointments'!$B:$B,$B11,'Appointments'!$F:$F,"Done",'Appointments'!$A:$A,">="&$C11,'Appointments'!$A:$A,"<="&$D11)) | F11: =IF(OR($B11="",$C11="",$D11=""),"",SUMIFS('Appointments'!$E:$E,'Appointments'!$B:$B,$B11,'Appointments'!$F:$F,"Done",'Appointments'!$A:$A,">="&$C11,'Appointments'!$A:$A,"<="&$D11,'Appointments'!$G:$G,"<>Yes"))
E12: =IF(OR($B12="",$C12="",$D12=""),"",SUMIFS('Appointments'!$E:$E,'Appointments'!$B:$B,$B12,'Appointments'!$F:$F,"Done",'Appointments'!$A:$A,">="&$C12,'Appointments'!$A:$A,"<="&$D12)) | F12: =IF(OR($B12="",$C12="",$D12=""),"",SUMIFS('Appointments'!$E:$E,'Appointments'!$B:$B,$B12,'Appointments'!$F:$F,"Done",'Appointments'!$A:$A,">="&$C12,'Appointments'!$A:$A,"<="&$D12,'Appointments'!$G:$G,"<>Yes"))
E13: =IF(OR($B13="",$C13="",$D13=""),"",SUMIFS('Appointments'!$E:$E,'Appointments'!$B:$B,$B13,'Appointments'!$F:$F,"Done",'Appointments'!$A:$A,">="&$C13,'Appointments'!$A:$A,"<="&$D13)) | F13: =IF(OR($B13="",$C13="",$D13=""),"",SUMIFS('Appointments'!$E:$E,'Appointments'!$B:$B,$B13,'Appointments'!$F:$F,"Done",'Appointments'!$A:$A,">="&$C13,'Appointments'!$A:$A,"<="&$D13,'Appointments'!$G:$G,"<>Yes"))
E14: =IF(OR($B14="",$C14="",$D14=""),"",SUMIFS('Appointments'!$E:$E,'Appointments'!$B:$B,$B14,'Appointments'!$F:$F,"Done",'Appointments'!$A:$A,">="&$C14,'Appointments'!$A:$A,"<="&$D14)) | F14: =IF(OR($B14="",$C14="",$D14=""),"",SUMIFS('Appointments'!$E:$E,'Appointments'!$B:$B,$B14,'Appointments'!$F:$F,"Done",'Appointments'!$A:$A,">="&$C14,'Appointments'!$A:$A,"<="&$D14,'Appointments'!$G:$G,"<>Yes"))
E15: =IF(OR($B15="",$C15="",$D15=""),"",SUMIFS('Appointments'!$E:$E,'Appointments'!$B:$B,$B15,'Appointments'!$F:$F,"Done",'Appointments'!$A:$A,">="&$C15,'Appointments'!$A:$A,"<="&$D15)) | F15: =IF(OR($B15="",$C15="",$D15=""),"",SUMIFS('Appointments'!$E:$E,'Appointments'!$B:$B,$B15,'Appointments'!$F:$F,"Done",'Appointments'!$A:$A,">="&$C15,'Appointments'!$A:$A,"<="&$D15,'Appointments'!$G:$G,"<>Yes"))
E16: =IF(OR($B16="",$C16="",$D16=""),"",SUMIFS('Appointments'!$E:$E,'Appointments'!$B:$B,$B16,'Appointments'!$F:$F,"Done",'Appointments'!$A:$A,">="&$C16,'Appointments'!$A:$A,"<="&$D16)) | F16: =IF(OR($B16="",$C16="",$D16=""),"",SUMIFS('Appointments'!$E:$E,'Appointments'!$B:$B,$B16,'Appointments'!$F:$F,"Done",'Appointments'!$A:$A,">="&$C16,'Appointments'!$A:$A,"<="&$D16,'Appointments'!$G:$G,"<>Yes"))
... E100: =IF(OR($B100="",$C100="",$D100=""),"",SUMIFS('Appointments'!$E:$E,'Appointments'!$B:$B,$B100,'Appointments'!$F:$F,"Done",'Appointments'!$A:$A,">="&$C100,'Appointments'!$A:$A,"<="&$D100)) | F100: =IF(OR($B100="",$C100="",$D100=""),"",SUMIFS('Appointments'!$E:$E,'Appointments'!$B:$B,$B100,'Appointments'!$F:$F,"Done",'Appointments'!$A:$A,">="&$C100,'Appointments'!$A:$A,"<="&$D100,'Appointments'!$G:$G,"<>Yes"))

Sheet Services & Rates
A1: Service | B1: Rate ($) | C1: Duration | D1: Notes
A2: Full Groom — Small | B2: 65 | C2: 90 minutes | D2: Under 25 lbs. Bath, dry, haircut, nails, ears
A3: Full Groom — Medium | B3: 85 | C3: 2 hours | D3: 25–60 lbs. Bath, dry, haircut, nails, ears
A4: Full Groom — Large | B4: 110 | C4: 2.5–3 hours | D4: 60+ lbs. Doodles / heavy coats may add a fee
A5: Bath & Brush | B5: 45 | C5: 60 minutes | D5: Bath, blow-dry, brush-out, nails, ears — no haircut
A6: Nail Trim | B6: 15 | C6: 15 minutes | D6: Walk-in friendly; +$5 with Dremel grinding
A7: De-shed Treatment | B7: 60 | C7: 90 minutes | D7: Double coats: undercoat rake + high-velocity dry
A8: Puppy Intro Groom | B8: 40 | C8: 45 minutes | D8: Under 6 months. Face/feet/tail tidy + handling practice
A32: Edit names and rates freely — the Appointments tab looks prices up from this list automatically. Service names here must match the dropdown picks exactly (they will, if you always pick from the dropdown).
