Workbook
Name ClientList: 'Clients'!$A$2:$A$200
Name ServiceList: 'Services & Rates'!$A$2:$A$30

Sheet START HERE
B2: WELCOME TO YOUR PET SITTER CLIENT CRM
B3: Made for pet sitters and dog walkers. Everything your business needs — clients, door codes, vet info, medications, schedule and money — in one place. No apps, no subscriptions, nothing to install.
B5: STEP 1 — MAKE YOUR OWN COPY (do this first!)
B6: USING GOOGLE SHEETS (free): 1. Go to sheets.google.com and sign in. 2. Click the folder icon (Open file picker), choose "Upload", and drop this file in. 3. It opens right in Google Sheets — then click File > Save as Google Sheets so it lives in your Drive forever.
B7: USING EXCEL: just open the file and File > Save As with your business name. Done.
B9: STEP 2 — KNOW YOUR COLORS
B10: WHITE cells = yours. Type anything.
B11: LIGHT GRAY cells = the spreadsheet's. They calculate themselves (rates, totals, the whole Dashboard). Don't type in them — if you ever do by accident, just press Ctrl+Z (Cmd+Z on Mac).
B12: Cells with a little arrow = dropdowns. Click the arrow and pick — never type these by hand, so names always match everywhere.
B14: STEP 3 — SET UP IN THIS ORDER
B15: 1. SERVICES & RATES — change the service names and prices to yours. The schedule fills in prices from this list automatically.
B16: 2. CLIENTS — one row per household. Door codes, alarm notes, key location, vet and emergency contact all live here, so everything you need mid-visit is one tap away on your phone.
... B30: Questions? Message me on Etsy any time — happy to help. Enjoy!

Sheet Dashboard
B2: PET SITTER CLIENT CRM — DASHBOARD
B3: ="Everything on this page updates itself — nothing to type here. Today: "&TEXT(TODAY(),"mmm d, yyyy")
B5: ACTIVE CLIENTS | E5: PETS UNDER CARE | H5: VISITS THIS WEEK
B6: =COUNTIF('Clients'!$L:$L,"Active") | E6: =COUNTA('Pets'!$B$2:$B$300) | H6: =COUNTIFS('Visit Schedule'!$A:$A,">="&(TODAY()-WEEKDAY(TODAY(),2)+1),'Visit Schedule'!$A:$A,"<="&(TODAY()-WEEKDAY(TODAY(),2)+1)+6,'Visit Schedule'!$G:$G,"<>Cancelled")
B8: VISITS TODAY | E8: REVENUE THIS MONTH | H8: UNPAID BALANCE
B9: =COUNTIFS('Visit Schedule'!$A:$A,TODAY(),'Visit Schedule'!$G:$G,"<>Cancelled") | E9: =SUMIFS('Visit Schedule'!$F:$F,'Visit Schedule'!$G:$G,"Done",'Visit Schedule'!$A:$A,">="&DATE(YEAR(TODAY()),MONTH(TODAY()),1),'Visit Schedule'!$A:$A,"<"&DATE(YEAR(TODAY()),MONTH(TODAY())+1,1)) | H9: =SUMIFS('Visit Schedule'!$F:$F,'Visit Schedule'!$G:$G,"Done",'Visit Schedule'!$H:$H,"<>Yes")
B12: TOP CLIENTS (completed visits, all time)
B13: Rank | C13: Client | H13: Revenue | O13: engine ↓ | P13: do not edit
B14: 1 | C14: =IFERROR(INDEX($P$14:$P$33,MATCH(LARGE($O$14:$O$33,1),$O$14:$O$33,0)),"—") | H14: =IFERROR(ROUND(LARGE($O$14:$O$33,1),2),"") | O14: =IF('Clients'!A2="","",SUMIFS('Visit Schedule'!$F:$F,'Visit Schedule'!$B:$B,'Clients'!A2,'Visit Schedule'!$G:$G,"Done")+ROW()/10000000) | P14: =IF($O14="","",'Clients'!A2)
B15: 2 | C15: =IFERROR(INDEX($P$14:$P$33,MATCH(LARGE($O$14:$O$33,2),$O$14:$O$33,0)),"—") | H15: =IFERROR(ROUND(LARGE($O$14:$O$33,2),2),"") | O15: =IF('Clients'!A3="","",SUMIFS('Visit Schedule'!$F:$F,'Visit Schedule'!$B:$B,'Clients'!A3,'Visit Schedule'!$G:$G,"Done")+ROW()/10000000) | P15: =IF($O15="","",'Clients'!A3)
B16: 3 | C16: =IFERROR(INDEX($P$14:$P$33,MATCH(LARGE($O$14:$O$33,3),$O$14:$O$33,0)),"—") | H16: =IFERROR(ROUND(LARGE($O$14:$O$33,3),2),"") | O16: =IF('Clients'!A4="","",SUMIFS('Visit Schedule'!$F:$F,'Visit Schedule'!$B:$B,'Clients'!A4,'Visit Schedule'!$G:$G,"Done")+ROW()/10000000) | P16: =IF($O16="","",'Clients'!A4)
B17: 4 | C17: =IFERROR(INDEX($P$14:$P$33,MATCH(LARGE($O$14:$O$33,4),$O$14:$O$33,0)),"—") | H17: =IFERROR(ROUND(LARGE($O$14:$O$33,4),2),"") | O17: =IF('Clients'!A5="","",SUMIFS('Visit Schedule'!$F:$F,'Visit Schedule'!$B:$B,'Clients'!A5,'Visit Schedule'!$G:$G,"Done")+ROW()/10000000) | P17: =IF($O17="","",'Clients'!A5)
B18: 5 | C18: =IFERROR(INDEX($P$14:$P$33,MATCH(LARGE($O$14:$O$33,5),$O$14:$O$33,0)),"—") | H18: =IFERROR(ROUND(LARGE($O$14:$O$33,5),2),"") | O18: =IF('Clients'!A6="","",SUMIFS('Visit Schedule'!$F:$F,'Visit Schedule'!$B:$B,'Clients'!A6,'Visit Schedule'!$G:$G,"Done")+ROW()/10000000) | P18: =IF($O18="","",'Clients'!A6)
O19: =IF('Clients'!A7="","",SUMIFS('Visit Schedule'!$F:$F,'Visit Schedule'!$B:$B,'Clients'!A7,'Visit Schedule'!$G:$G,"Done")+ROW()/10000000) | P19: =IF($O19="","",'Clients'!A7)
O20: =IF('Clients'!A8="","",SUMIFS('Visit Schedule'!$F:$F,'Visit Schedule'!$B:$B,'Clients'!A8,'Visit Schedule'!$G:$G,"Done")+ROW()/10000000) | P20: =IF($O20="","",'Clients'!A8)
B21: Top-client list scans your first 20 client rows. Hidden columns O-P do the math — leave them alone (Format > Unhide if you're curious). | O21: =IF('Clients'!A9="","",SUMIFS('Visit Schedule'!$F:$F,'Visit Schedule'!$B:$B,'Clients'!A9,'Visit Schedule'!$G:$G,"Done")+ROW()/10000000) | P21: =IF($O21="","",'Clients'!A9)
O22: =IF('Clients'!A10="","",SUMIFS('Visit Schedule'!$F:$F,'Visit Schedule'!$B:$B,'Clients'!A10,'Visit Schedule'!$G:$G,"Done")+ROW()/10000000) | P22: =IF($O22="","",'Clients'!A10)
O23: =IF('Clients'!A11="","",SUMIFS('Visit Schedule'!$F:$F,'Visit Schedule'!$B:$B,'Clients'!A11,'Visit Schedule'!$G:$G,"Done")+ROW()/10000000) | P23: =IF($O23="","",'Clients'!A11)
O24: =IF('Clients'!A12="","",SUMIFS('Visit Schedule'!$F:$F,'Visit Schedule'!$B:$B,'Clients'!A12,'Visit Schedule'!$G:$G,"Done")+ROW()/10000000) | P24: =IF($O24="","",'Clients'!A12)
O25: =IF('Clients'!A13="","",SUMIFS('Visit Schedule'!$F:$F,'Visit Schedule'!$B:$B,'Clients'!A13,'Visit Schedule'!$G:$G,"Done")+ROW()/10000000) | P25: =IF($O25="","",'Clients'!A13)
O26: =IF('Clients'!A14="","",SUMIFS('Visit Schedule'!$F:$F,'Visit Schedule'!$B:$B,'Clients'!A14,'Visit Schedule'!$G:$G,"Done")+ROW()/10000000) | P26: =IF($O26="","",'Clients'!A14)
O27: =IF('Clients'!A15="","",SUMIFS('Visit Schedule'!$F:$F,'Visit Schedule'!$B:$B,'Clients'!A15,'Visit Schedule'!$G:$G,"Done")+ROW()/10000000) | P27: =IF($O27="","",'Clients'!A15)
O28: =IF('Clients'!A16="","",SUMIFS('Visit Schedule'!$F:$F,'Visit Schedule'!$B:$B,'Clients'!A16,'Visit Schedule'!$G:$G,"Done")+ROW()/10000000) | P28: =IF($O28="","",'Clients'!A16)
O29: =IF('Clients'!A17="","",SUMIFS('Visit Schedule'!$F:$F,'Visit Schedule'!$B:$B,'Clients'!A17,'Visit Schedule'!$G:$G,"Done")+ROW()/10000000) | P29: =IF($O29="","",'Clients'!A17)
O30: =IF('Clients'!A18="","",SUMIFS('Visit Schedule'!$F:$F,'Visit Schedule'!$B:$B,'Clients'!A18,'Visit Schedule'!$G:$G,"Done")+ROW()/10000000) | P30: =IF($O30="","",'Clients'!A18)
O31: =IF('Clients'!A19="","",SUMIFS('Visit Schedule'!$F:$F,'Visit Schedule'!$B:$B,'Clients'!A19,'Visit Schedule'!$G:$G,"Done")+ROW()/10000000) | P31: =IF($O31="","",'Clients'!A19)
O32: =IF('Clients'!A20="","",SUMIFS('Visit Schedule'!$F:$F,'Visit Schedule'!$B:$B,'Clients'!A20,'Visit Schedule'!$G:$G,"Done")+ROW()/10000000) | P32: =IF($O32="","",'Clients'!A20)
O33: =IF('Clients'!A21="","",SUMIFS('Visit Schedule'!$F:$F,'Visit Schedule'!$B:$B,'Clients'!A21,'Visit Schedule'!$G:$G,"Done")+ROW()/10000000) | P33: =IF($O33="","",'Clients'!A21)

Sheet Clients
A1: Client Name | B1: Phone | C1: Email | D1: Home Address | E1: Door / Gate Code | F1: Alarm Instructions | G1: Key Location | H1: Emergency Contact (name & phone) | I1: Vet Clinic | J1: Vet Phone | K1: Preferred Contact | L1: Status | M1: Notes
A2: Sarah Mitchell | B2: (555) 201-8843 | C2: sarah.m@example.com | D2: 42 Birchwood Ln | E2: Garage keypad: 4821# | F2: Panel by front door — code 0515, disarm within 60 sec | G2: Lockbox on porch rail — 7734 | H2: Tom Mitchell (555) 201-8850 | I2: Lakeview Animal Hospital | J2: (555) 640-2210 | K2: Text | L2: Active | M2: SAMPLE ROW — delete me
A3: Dana Whitfield | B3: (555) 318-2276 | C3: danaw@example.com | D3: 980 Alder Ct, Unit B | E3: Gate: 2299 / Door: key only | F3: No alarm | G3: Under ceramic frog, left of steps | H3: Priya Nair (sister) (555) 318-9901 | I3: Eastside Vet Clinic | J3: (555) 772-0184 | K3: Email | L3: Active | M3: SAMPLE ROW — delete me
A4: Marcus Lee | B4: (555) 467-9032 | C4: marcus.lee@example.com | D4: 17 Harborview Dr | E4: Smart lock — code texted weekly | F4: Alarm app on my phone (shared access) | G4: N/A — smart lock | H4: Jen Lee (555) 467-9033 | I4: Harbor Animal Hospital | J4: (555) 903-3341 | K4: Call | L4: Waitlist | M4: SAMPLE ROW — delete me

Sheet Pets
A1: Client | B1: Pet Name | C1: Species | D1: Breed | E1: Age | F1: Feeding Instructions | G1: Medications & Schedule | H1: Walk Routine | I1: Behavior Notes / Warnings | J1: Grooming Notes
A2: Sarah Mitchell | B2: Biscuit | C2: Dog | D2: Golden Retriever | E2: 4 | F2: 1 cup kibble 7am & 6pm; treats after walks OK | G2: None | H2: 30 min neighborhood loop; pulls hard at squirrels | I2: Friendly with all dogs & people | J2: Brush weekly — SAMPLE ROW, delete me
A3: Sarah Mitchell | B3: Clover | C3: Cat | D3: Domestic Shorthair | E3: 7 | F3: 1/2 can wet food 8am; dry food always out | G3: Thyroid pill 8am — hide in Churu treat | H3: Indoor only | I3: Shy — hides under guest bed from strangers | J3: SAMPLE ROW — delete me
A4: Dana Whitfield | B4: Rocko | C4: Dog | D4: Boxer mix | E4: 2 | F4: 2 cups kibble 6pm only; no chicken (allergy) | G4: None | H4: 60 min run or fetch at Alder Park | I4: CAUTION: reactive to bikes & skateboards — short leash near paths | J4: SAMPLE ROW — delete me
A5: Marcus Lee | B5: Pepper | C5: Dog | D5: Mini Schnauzer | E5: 9 | F5: 1/2 cup senior kibble 7am & 5pm | G5: Rimadyl 25mg with dinner | H5: 20 min gentle walk, no stairs | I5: Barks at mail carriers — all noise, no bite | J5: Grooming every 6 weeks — SAMPLE ROW, delete me

Sheet Visit Schedule
A1: Date | B1: Client | C1: Pet(s) | D1: Service | E1: Recurring? | F1: Rate ($) | G1: Status | H1: Paid? | I1: Notes
A2: =TODAY()+0 | B2: Sarah Mitchell | C2: Biscuit + Clover | D2: Drop-in Visit | E2: Weekly | F2: =IF($D2="","",IFERROR(VLOOKUP($D2,'Services & Rates'!$A$2:$B$30,2,FALSE),"")) | G2: Booked | H2: No | I2: SAMPLE — today's visits glow green
A3: =TODAY()-3 | B3: Dana Whitfield | C3: Rocko | D3: Walk 60 min | E3: Weekly | F3: =IF($D3="","",IFERROR(VLOOKUP($D3,'Services & Rates'!$A$2:$B$30,2,FALSE),"")) | G3: Done | H3: No | I3: SAMPLE — done + unpaid turns red
A4: =TODAY()-7 | B4: Sarah Mitchell | C4: Biscuit | D4: Walk 30 min | E4: Weekly | F4: =IF($D4="","",IFERROR(VLOOKUP($D4,'Services & Rates'!$A$2:$B$30,2,FALSE),"")) | G4: Done | H4: Yes | I4: SAMPLE ROW — delete me
A5: =DATE(YEAR(TODAY()),MONTH(TODAY()),1) | B5: Dana Whitfield | C5: Rocko | D5: Walk 60 min | E5: Weekly | F5: =IF($D5="","",IFERROR(VLOOKUP($D5,'Services & Rates'!$A$2:$B$30,2,FALSE),"")) | G5: Done | H5: Yes | I5: SAMPLE ROW — delete me
A6: =TODAY()-10 | B6: Marcus Lee | C6: Pepper | D6: Overnight Stay | E6: One-off | F6: =IF($D6="","",IFERROR(VLOOKUP($D6,'Services & Rates'!$A$2:$B$30,2,FALSE),"")) | G6: Done | H6: No | I6: SAMPLE ROW — delete me
A7: =TODAY()+2 | B7: Marcus Lee | C7: Pepper | D7: Walk 30 min | E7: Biweekly | F7: =IF($D7="","",IFERROR(VLOOKUP($D7,'Services & Rates'!$A$2:$B$30,2,FALSE),"")) | G7: Booked | H7: No | I7: SAMPLE ROW — delete me
F8: =IF($D8="","",IFERROR(VLOOKUP($D8,'Services & Rates'!$A$2:$B$30,2,FALSE),""))
F9: =IF($D9="","",IFERROR(VLOOKUP($D9,'Services & Rates'!$A$2:$B$30,2,FALSE),""))
F10: =IF($D10="","",IFERROR(VLOOKUP($D10,'Services & Rates'!$A$2:$B$30,2,FALSE),""))
F11: =IF($D11="","",IFERROR(VLOOKUP($D11,'Services & Rates'!$A$2:$B$30,2,FALSE),""))
F12: =IF($D12="","",IFERROR(VLOOKUP($D12,'Services & Rates'!$A$2:$B$30,2,FALSE),""))
F13: =IF($D13="","",IFERROR(VLOOKUP($D13,'Services & Rates'!$A$2:$B$30,2,FALSE),""))
F14: =IF($D14="","",IFERROR(VLOOKUP($D14,'Services & Rates'!$A$2:$B$30,2,FALSE),""))
F15: =IF($D15="","",IFERROR(VLOOKUP($D15,'Services & Rates'!$A$2:$B$30,2,FALSE),""))
F16: =IF($D16="","",IFERROR(VLOOKUP($D16,'Services & Rates'!$A$2:$B$30,2,FALSE),""))
F17: =IF($D17="","",IFERROR(VLOOKUP($D17,'Services & Rates'!$A$2:$B$30,2,FALSE),""))
F18: =IF($D18="","",IFERROR(VLOOKUP($D18,'Services & Rates'!$A$2:$B$30,2,FALSE),""))
F19: =IF($D19="","",IFERROR(VLOOKUP($D19,'Services & Rates'!$A$2:$B$30,2,FALSE),""))
... F250: =IF($D250="","",IFERROR(VLOOKUP($D250,'Services & Rates'!$A$2:$B$30,2,FALSE),""))

Sheet Invoices & Payments
A1: Invoice # | B1: Client | C1: Period Start | D1: Period End | E1: Invoice Total ($) | F1: Balance Due ($) | G1: Date Sent | H1: Date Paid | I1: Status | J1: Notes
A2: INV-1001 | B2: Sarah Mitchell | C2: =TODAY()-14 | D2: =TODAY()-5 | E2: =IF(OR($B2="",$C2="",$D2=""),"",SUMIFS('Visit Schedule'!$F:$F,'Visit Schedule'!$B:$B,$B2,'Visit Schedule'!$G:$G,"Done",'Visit Schedule'!$A:$A,">="&$C2,'Visit Schedule'!$A:$A,"<="&$D2)) | F2: =IF(OR($B2="",$C2="",$D2=""),"",SUMIFS('Visit Schedule'!$F:$F,'Visit Schedule'!$B:$B,$B2,'Visit Schedule'!$G:$G,"Done",'Visit Schedule'!$A:$A,">="&$C2,'Visit Schedule'!$A:$A,"<="&$D2,'Visit Schedule'!$H:$H,"<>Yes")) | G2: =TODAY()-4 | H2: =TODAY()-2 | I2: Paid | J2: SAMPLE ROW — delete me
A3: INV-1002 | B3: Dana Whitfield | C3: =TODAY()-6 | D3: =TODAY()+0 | E3: =IF(OR($B3="",$C3="",$D3=""),"",SUMIFS('Visit Schedule'!$F:$F,'Visit Schedule'!$B:$B,$B3,'Visit Schedule'!$G:$G,"Done",'Visit Schedule'!$A:$A,">="&$C3,'Visit Schedule'!$A:$A,"<="&$D3)) | F3: =IF(OR($B3="",$C3="",$D3=""),"",SUMIFS('Visit Schedule'!$F:$F,'Visit Schedule'!$B:$B,$B3,'Visit Schedule'!$G:$G,"Done",'Visit Schedule'!$A:$A,">="&$C3,'Visit Schedule'!$A:$A,"<="&$D3,'Visit Schedule'!$H:$H,"<>Yes")) | G3: =TODAY()+0 | I3: Sent | J3: SAMPLE ROW — delete me
A4: INV-1003 | B4: Marcus Lee | C4: =TODAY()-20 | D4: =TODAY()-8 | E4: =IF(OR($B4="",$C4="",$D4=""),"",SUMIFS('Visit Schedule'!$F:$F,'Visit Schedule'!$B:$B,$B4,'Visit Schedule'!$G:$G,"Done",'Visit Schedule'!$A:$A,">="&$C4,'Visit Schedule'!$A:$A,"<="&$D4)) | F4: =IF(OR($B4="",$C4="",$D4=""),"",SUMIFS('Visit Schedule'!$F:$F,'Visit Schedule'!$B:$B,$B4,'Visit Schedule'!$G:$G,"Done",'Visit Schedule'!$A:$A,">="&$C4,'Visit Schedule'!$A:$A,"<="&$D4,'Visit Schedule'!$H:$H,"<>Yes")) | G4: =TODAY()-18 | I4: Overdue | J4: SAMPLE ROW — delete me
E5: =IF(OR($B5="",$C5="",$D5=""),"",SUMIFS('Visit Schedule'!$F:$F,'Visit Schedule'!$B:$B,$B5,'Visit Schedule'!$G:$G,"Done",'Visit Schedule'!$A:$A,">="&$C5,'Visit Schedule'!$A:$A,"<="&$D5)) | F5: =IF(OR($B5="",$C5="",$D5=""),"",SUMIFS('Visit Schedule'!$F:$F,'Visit Schedule'!$B:$B,$B5,'Visit Schedule'!$G:$G,"Done",'Visit Schedule'!$A:$A,">="&$C5,'Visit Schedule'!$A:$A,"<="&$D5,'Visit Schedule'!$H:$H,"<>Yes"))
E6: =IF(OR($B6="",$C6="",$D6=""),"",SUMIFS('Visit Schedule'!$F:$F,'Visit Schedule'!$B:$B,$B6,'Visit Schedule'!$G:$G,"Done",'Visit Schedule'!$A:$A,">="&$C6,'Visit Schedule'!$A:$A,"<="&$D6)) | F6: =IF(OR($B6="",$C6="",$D6=""),"",SUMIFS('Visit Schedule'!$F:$F,'Visit Schedule'!$B:$B,$B6,'Visit Schedule'!$G:$G,"Done",'Visit Schedule'!$A:$A,">="&$C6,'Visit Schedule'!$A:$A,"<="&$D6,'Visit Schedule'!$H:$H,"<>Yes"))
E7: =IF(OR($B7="",$C7="",$D7=""),"",SUMIFS('Visit Schedule'!$F:$F,'Visit Schedule'!$B:$B,$B7,'Visit Schedule'!$G:$G,"Done",'Visit Schedule'!$A:$A,">="&$C7,'Visit Schedule'!$A:$A,"<="&$D7)) | F7: =IF(OR($B7="",$C7="",$D7=""),"",SUMIFS('Visit Schedule'!$F:$F,'Visit Schedule'!$B:$B,$B7,'Visit Schedule'!$G:$G,"Done",'Visit Schedule'!$A:$A,">="&$C7,'Visit Schedule'!$A:$A,"<="&$D7,'Visit Schedule'!$H:$H,"<>Yes"))
E8: =IF(OR($B8="",$C8="",$D8=""),"",SUMIFS('Visit Schedule'!$F:$F,'Visit Schedule'!$B:$B,$B8,'Visit Schedule'!$G:$G,"Done",'Visit Schedule'!$A:$A,">="&$C8,'Visit Schedule'!$A:$A,"<="&$D8)) | F8: =IF(OR($B8="",$C8="",$D8=""),"",SUMIFS('Visit Schedule'!$F:$F,'Visit Schedule'!$B:$B,$B8,'Visit Schedule'!$G:$G,"Done",'Visit Schedule'!$A:$A,">="&$C8,'Visit Schedule'!$A:$A,"<="&$D8,'Visit Schedule'!$H:$H,"<>Yes"))
E9: =IF(OR($B9="",$C9="",$D9=""),"",SUMIFS('Visit Schedule'!$F:$F,'Visit Schedule'!$B:$B,$B9,'Visit Schedule'!$G:$G,"Done",'Visit Schedule'!$A:$A,">="&$C9,'Visit Schedule'!$A:$A,"<="&$D9)) | F9: =IF(OR($B9="",$C9="",$D9=""),"",SUMIFS('Visit Schedule'!$F:$F,'Visit Schedule'!$B:$B,$B9,'Visit Schedule'!$G:$G,"Done",'Visit Schedule'!$A:$A,">="&$C9,'Visit Schedule'!$A:$A,"<="&$D9,'Visit Schedule'!$H:$H,"<>Yes"))
E10: =IF(OR($B10="",$C10="",$D10=""),"",SUMIFS('Visit Schedule'!$F:$F,'Visit Schedule'!$B:$B,$B10,'Visit Schedule'!$G:$G,"Done",'Visit Schedule'!$A:$A,">="&$C10,'Visit Schedule'!$A:$A,"<="&$D10)) | F10: =IF(OR($B10="",$C10="",$D10=""),"",SUMIFS('Visit Schedule'!$F:$F,'Visit Schedule'!$B:$B,$B10,'Visit Schedule'!$G:$G,"Done",'Visit Schedule'!$A:$A,">="&$C10,'Visit Schedule'!$A:$A,"<="&$D10,'Visit Schedule'!$H:$H,"<>Yes"))
E11: =IF(OR($B11="",$C11="",$D11=""),"",SUMIFS('Visit Schedule'!$F:$F,'Visit Schedule'!$B:$B,$B11,'Visit Schedule'!$G:$G,"Done",'Visit Schedule'!$A:$A,">="&$C11,'Visit Schedule'!$A:$A,"<="&$D11)) | F11: =IF(OR($B11="",$C11="",$D11=""),"",SUMIFS('Visit Schedule'!$F:$F,'Visit Schedule'!$B:$B,$B11,'Visit Schedule'!$G:$G,"Done",'Visit Schedule'!$A:$A,">="&$C11,'Visit Schedule'!$A:$A,"<="&$D11,'Visit Schedule'!$H:$H,"<>Yes"))
E12: =IF(OR($B12="",$C12="",$D12=""),"",SUMIFS('Visit Schedule'!$F:$F,'Visit Schedule'!$B:$B,$B12,'Visit Schedule'!$G:$G,"Done",'Visit Schedule'!$A:$A,">="&$C12,'Visit Schedule'!$A:$A,"<="&$D12)) | F12: =IF(OR($B12="",$C12="",$D12=""),"",SUMIFS('Visit Schedule'!$F:$F,'Visit Schedule'!$B:$B,$B12,'Visit Schedule'!$G:$G,"Done",'Visit Schedule'!$A:$A,">="&$C12,'Visit Schedule'!$A:$A,"<="&$D12,'Visit Schedule'!$H:$H,"<>Yes"))
E13: =IF(OR($B13="",$C13="",$D13=""),"",SUMIFS('Visit Schedule'!$F:$F,'Visit Schedule'!$B:$B,$B13,'Visit Schedule'!$G:$G,"Done",'Visit Schedule'!$A:$A,">="&$C13,'Visit Schedule'!$A:$A,"<="&$D13)) | F13: =IF(OR($B13="",$C13="",$D13=""),"",SUMIFS('Visit Schedule'!$F:$F,'Visit Schedule'!$B:$B,$B13,'Visit Schedule'!$G:$G,"Done",'Visit Schedule'!$A:$A,">="&$C13,'Visit Schedule'!$A:$A,"<="&$D13,'Visit Schedule'!$H:$H,"<>Yes"))
E14: =IF(OR($B14="",$C14="",$D14=""),"",SUMIFS('Visit Schedule'!$F:$F,'Visit Schedule'!$B:$B,$B14,'Visit Schedule'!$G:$G,"Done",'Visit Schedule'!$A:$A,">="&$C14,'Visit Schedule'!$A:$A,"<="&$D14)) | F14: =IF(OR($B14="",$C14="",$D14=""),"",SUMIFS('Visit Schedule'!$F:$F,'Visit Schedule'!$B:$B,$B14,'Visit Schedule'!$G:$G,"Done",'Visit Schedule'!$A:$A,">="&$C14,'Visit Schedule'!$A:$A,"<="&$D14,'Visit Schedule'!$H:$H,"<>Yes"))
E15: =IF(OR($B15="",$C15="",$D15=""),"",SUMIFS('Visit Schedule'!$F:$F,'Visit Schedule'!$B:$B,$B15,'Visit Schedule'!$G:$G,"Done",'Visit Schedule'!$A:$A,">="&$C15,'Visit Schedule'!$A:$A,"<="&$D15)) | F15: =IF(OR($B15="",$C15="",$D15=""),"",SUMIFS('Visit Schedule'!$F:$F,'Visit Schedule'!$B:$B,$B15,'Visit Schedule'!$G:$G,"Done",'Visit Schedule'!$A:$A,">="&$C15,'Visit Schedule'!$A:$A,"<="&$D15,'Visit Schedule'!$H:$H,"<>Yes"))
E16: =IF(OR($B16="",$C16="",$D16=""),"",SUMIFS('Visit Schedule'!$F:$F,'Visit Schedule'!$B:$B,$B16,'Visit Schedule'!$G:$G,"Done",'Visit Schedule'!$A:$A,">="&$C16,'Visit Schedule'!$A:$A,"<="&$D16)) | F16: =IF(OR($B16="",$C16="",$D16=""),"",SUMIFS('Visit Schedule'!$F:$F,'Visit Schedule'!$B:$B,$B16,'Visit Schedule'!$G:$G,"Done",'Visit Schedule'!$A:$A,">="&$C16,'Visit Schedule'!$A:$A,"<="&$D16,'Visit Schedule'!$H:$H,"<>Yes"))
... E100: =IF(OR($B100="",$C100="",$D100=""),"",SUMIFS('Visit Schedule'!$F:$F,'Visit Schedule'!$B:$B,$B100,'Visit Schedule'!$G:$G,"Done",'Visit Schedule'!$A:$A,">="&$C100,'Visit Schedule'!$A:$A,"<="&$D100)) | F100: =IF(OR($B100="",$C100="",$D100=""),"",SUMIFS('Visit Schedule'!$F:$F,'Visit Schedule'!$B:$B,$B100,'Visit Schedule'!$G:$G,"Done",'Visit Schedule'!$A:$A,">="&$C100,'Visit Schedule'!$A:$A,"<="&$D100,'Visit Schedule'!$H:$H,"<>Yes"))

Sheet Services & Rates
A1: Service | B1: Rate ($) | C1: Duration | D1: Notes
A2: Walk 30 min | B2: 22 | C2: 30 minutes | D2: One dog; +$8 per extra dog
A3: Walk 60 min | B3: 35 | C3: 60 minutes | D3: One dog; +$10 per extra dog
A4: Drop-in Visit | B4: 28 | C4: 30 minutes | D4: Feeding, litter, playtime, meds
A5: Overnight Stay | B5: 85 | C5: 12 hours | D5: In client's home, 7pm-7am
A6: Boarding (per night) | B6: 65 | C6: 24 hours | D6: In sitter's home
A32: Edit names and rates freely — the Visit Schedule looks prices up from this list automatically. Service names here must match the dropdown picks exactly (they will, if you always pick from the dropdown).
